MANIFEST.in
README.rst
__init__.py
setup.cfg
setup.py
dist/django_msp_polizas-0.0.1/__init__.py
dist/django_msp_polizas-0.0.1/django_msp_polizas/__init__.py
dist/django_msp_polizas-0.0.1/django_msp_polizas/modulos/__init__.py
dist/django_msp_polizas-0.0.1/django_msp_polizas/modulos/polizas/__init__.py
dist/django_msp_polizas-0.0.1/django_msp_polizas/modulos/preferencias/__init__.py
django_msp_polizas/__init__.py
django_msp_polizas/__init__.pyc
django_msp_polizas/autocomplete_light_registry.pyc
django_msp_polizas/config.pyc
django_msp_polizas/models.pyc
django_msp_polizas/urls.pyc
django_msp_polizas/views.pyc
django_msp_polizas.egg-info/PKG-INFO
django_msp_polizas.egg-info/SOURCES.txt
django_msp_polizas.egg-info/dependency_links.txt
django_msp_polizas.egg-info/top_level.txt
django_msp_polizas/modulos/__init__.py
django_msp_polizas/modulos/__init__.pyc
django_msp_polizas/modulos/polizas/__init__.py
django_msp_polizas/modulos/polizas/__init__.pyc
django_msp_polizas/modulos/polizas/models.pyc
django_msp_polizas/modulos/polizas/urls.pyc
django_msp_polizas/modulos/polizas/views.pyc
django_msp_polizas/modulos/preferencias/__init__.py
django_msp_polizas/modulos/preferencias/__init__.pyc
django_msp_polizas/modulos/preferencias/forms.pyc
django_msp_polizas/modulos/preferencias/models.pyc
django_msp_polizas/modulos/preferencias/urls.pyc
django_msp_polizas/modulos/preferencias/views.pyc
django_msp_polizas/static/django_msp_polizas/js/polizas.js
django_msp_polizas/templates/django_msp_polizas/base.html
django_msp_polizas/templates/django_msp_polizas/index.html
django_msp_polizas/templates/django_msp_polizas/polizas/poliza_list.html
django_msp_polizas/templates/django_msp_polizas/preferencias/preferencias.html